aejuice_kafka_consumer/__init__.py
aejuice_kafka_consumer/aejuice_kafka_consumer.py
aejuice_kafka_consumer/aejuice_kafka_consumer_test.py
aejuice_kafka_consumer/health_check.py
aejuice_kafka_consumer/health_check_runner.py
aejuice_kafka_consumer/process_killer.py
aejuice_kafka_consumer/state_storage.py
aejuice_kafka_consumer-1.0.1.dist-info/WHEEL
aejuice_kafka_consumer-1.0.1.dist-info/METADATA
aejuice_kafka_consumer-1.0.1.dist-info/RECORD
