Metadata-Version: 2.1
Name: aejuice-kafka-consumer
Version: 1.0.1
Summary: Logger package for using with AEJuice python services
License: MIT
Author: chloyka
Author-email: chloyka@gmail.com
Requires-Python: >=3.7,<4.0
Classifier: License :: OSI Approved :: MIT License
Classifier: Programming Language :: Python :: 3
Classifier: Programming Language :: Python :: 3.10
Classifier: Programming Language :: Python :: 3.7
Classifier: Programming Language :: Python :: 3.8
Classifier: Programming Language :: Python :: 3.9
